<Updates>
 <ApplicationName>{AnyApplication}</ApplicationName>
 <ApplicationVersion>1.0.0</ApplicationVersion>
 <Checksum>true</Checksum>
 <PackageUpdate>
  <Name>org.rxlaboratory.ifw.maintenancetool</Name>
  <DisplayName>The RxLaboratory Maintenance Tool</DisplayName>
  <Version>1.0.3</Version>
  <Description>The RxLaboratory maintenance tool is used to update or uninstall the Rx Open Tools.</Description>
  <Essential>true</Essential>
  <Virtual>true</Virtual>
  <ReleaseDate>2022-12-24</ReleaseDate>
  <Script>installscript.js</Script>
  <UpdateFile UncompressedSize="29054897" OS="Any" CompressedSize="10915688"/>
  <DownloadableArchives>content.7z</DownloadableArchives>
  <UserInterfaces>targetWidget.ui,finishWidget.ui</UserInterfaces>
  <SHA1>00ff053137d3fcf5c5f545da49c11f66edf2a874</SHA1>
 </PackageUpdate>
 <SHA1>df57825c9b578ecca3c7b3c83de58597b5d85dcd</SHA1>
 <MetadataName>2024-02-06-1254_meta.7z</MetadataName>
</Updates>
